nephos/__init__.py
nephos/deploy.py
nephos/runners.py
nephos/composer/__init__.py
nephos/composer/connection_template.py
nephos/composer/helpers.py
nephos/composer/install.py
nephos/composer/upgrade.py
nephos/extras/Lets_Encrypt_Authority_X3.pem
nephos/extras/helm-rbac.yaml
nephos/fabric/__init__.py
nephos/fabric/ca.py
nephos/fabric/crypto.py
nephos/fabric/ord.py
nephos/fabric/peer.py
nephos/fabric/settings.py
nephos/fabric/utils.py
nephos/helpers/__init__.py
nephos/helpers/executer.py
nephos/helpers/helm.py
nephos/helpers/k8s.py
nephos/helpers/misc.py
nephos-0.4.4.dist-info/LICENSE
nephos-0.4.4.dist-info/METADATA
nephos-0.4.4.dist-info/WHEEL
nephos-0.4.4.dist-info/top_level.txt
nephos-0.4.4.dist-info/RECORD
