Metadata-Version: 2.1
Name: nephos
Version: 0.4.4
Summary: Deployer for Hyperledger Fabric networks onto Kubernetes
Home-page: https://github.com/aidtechnology/nephos
Author: Alejandro (Sasha) Vicente Grabovetsky
Author-email: sasha@aid.technology
License: MIT
Platform: UNKNOWN
Classifier: License :: OSI Approved :: MIT License
Classifier: Programming Language :: Python
Classifier: Programming Language :: Python :: 3
Classifier: Programming Language :: Python :: 3.7
Classifier: Programming Language :: Python :: Implementation :: CPython
Classifier: Programming Language :: Python :: Implementation :: PyPy
Requires-Python: >=3.7.0
Requires-Dist: blessings
Requires-Dist: click
Requires-Dist: kubernetes
Requires-Dist: pygments
